research_analyzer/__init__.py
research_analyzer/analysis.py
research_analyzer/config.py
research_analyzer/embedding.py
research_analyzer/metrics.py
research_analyzer/networks.py
research_analyzer/preprocessing.py
research_analyzer/topics.py
research_analyzer/visualization.py
research_analyzer-0.1.0.dist-info/METADATA
research_analyzer-0.1.0.dist-info/WHEEL
research_analyzer-0.1.0.dist-info/top_level.txt
research_analyzer-0.1.0.dist-info/RECORD
